{
    "$schema": "http://schema.management.azure.com/schemas/2015-01-01/deploymentTemplate.json",
    "contentVersion": "1.0.0.0",
    "parameters": {
        "name": {
            "type": "String"
        },
        "location": {
            "type": "String"
        },
        "apiVersion": {
            "type": "String"
        },
        "publicNetworkAccess": {
            "type": "String"
        },
        "immutabilityState": {
            "type": "String"
        },
        "standardTierStorageRedundancy": {
            "type": "String"
        },
        "crossRegionRestore": {
            "type": "String"
        }
    },
    "resources": [
        {
            "type": "Microsoft.RecoveryServices/vaults",
            "apiVersion": "[parameters('apiVersion')]",
            "name": "[parameters('name')]",
            "location": "[parameters('location')]",
            "sku": {
                "name": "RS0",
                "tier": "Standard"
            },
            "properties": {
                "publicNetworkAccess": "[parameters('publicNetworkAccess')]",
                "securitySettings": {
                    "immutabilitySettings": {
                        "state": "[parameters('immutabilityState')]"
                    }
                },
                "redundancySettings": {
                    "standardTierStorageRedundancy": "[parameters('standardTierStorageRedundancy')]",
                    "crossRegionRestore": "[parameters('crossRegionRestore')]"
                }
            }
        }
    ]
}